<Alloy>
<View layout="vertical"  top="10" left="10" right="10" backgroundColor="white" class="container" height="Titanium.UI.SIZE">
	<View layout="horizontal" height="80">
		<Require src="toggle"></Require>
		<Label class="title" color="black" width="75%" textAlign="Ti.UI.TEXT_ALIGNMENT_CENTER">About Us</Label>
	</View>
	<ScrollView id="mainScroll" layout="vertical" height="Ti.UI.SIZE" overScrollMode="Titanium.UI.Android.OVER_SCROLL_NEVER">
		<ScrollView id="main" layout="vertical" height="200" overScrollMode="Titanium.UI.Android.OVER_SCROLL_NEVER" >
			<Label class="aboutContent" width="85%">It was in 1959 that SISSONS PAINTS (EAST) SDN BHD first started in Malaysia, although SISSONS' technology in paint making goes back 185 years when Sissons Brothers founded a company in HULL, England in 1803. SISSONS' well-known trademark of 'THE MEN AND PLANK' has been in use since 1910. </Label>	
		</ScrollView>
		<View layout="vertical" backgroundColor="white" height="Titanium.UI.SIZE">
			<ImageView image="/images/scroll_up.png" backgroundColor="#white" width="Titanium.UI.FILL" />
		
			<Label class="title" color="black" bottom="10" width="75%" textAlign="Ti.UI.TEXT_ALIGNMENT_LEFT">Email</Label>
			<View layout="horizontal" height="40" top="10" width="90%" horizontalWrap="true">
				<Label class="description_content" color="#6E6E6E" width="30%">Name</Label>	
				<TextField id="name" class="inputField" width="60%" />
			</View>
			<View layout="horizontal" height="40" top="10" width="90%" horizontalWrap="true">
				<Label class="description_content" color="#6E6E6E" width="30%">Email</Label>	
				<TextField id="email" class="inputField" width="60%" />
			</View>
			<View  layout="horizontal" height="100" top="10" bottom="15" width="90%" horizontalWrap="true">
				<Label class="description_content" color="#6E6E6E" width="30%" top="0">Message</Label>	
				<TextArea id="message" color="#888" textAlign="left" width="60%" height="100" borderColor="#888" />
			</View>
			 
	    </View>
	    <View backgroundColor="green" height="60" bottom="0">
			<ImageView image="/images/tool_bar.jpg" height="60" width="Titanium.UI.FILL" />
			<ImageView id="contactButton" image="/images/icon_email.png" onClick="submitContactForm" height="40" />
	    </View>
    </ScrollView>
	<!--</ScrollView>-->
	
</View>
</Alloy>